tinderapi/TinderSQLite.py
tinderapi/__init__.py
tinderapi/scave.py
tinderapi/telegram.py
tinderapi/tinder.py
tinderapi-1.0.6.dist-info/METADATA
tinderapi-1.0.6.dist-info/WHEEL
tinderapi-1.0.6.dist-info/top_level.txt
tinderapi-1.0.6.dist-info/RECORD
