Metadata-Version: 2.1
Name: tinderapi
Version: 1.0.6
Summary: Tinder API - You don't need to hold your phone anymore to submit tinder likes
Author: Aymane Elhattab
Author-email: <aymane.elhattab.master@gmail.com>
License: UNKNOWN
Keywords: tinder,tinder client,bot,api
Platform: UNKNOWN
Classifier: Intended Audience :: Developers
Classifier: Programming Language :: Python :: 3
Classifier: Operating System :: Unix
Classifier: Operating System :: MacOS :: MacOS X
Classifier: Operating System :: Microsoft :: Windows
Requires-Dist: requests
